xethhung12_minio_common/__init__.py
xethhung12_minio_common/common.py
xethhung12_minio_common-0.0.3.dist-info/METADATA
xethhung12_minio_common-0.0.3.dist-info/WHEEL
xethhung12_minio_common-0.0.3.dist-info/licenses/LICENSE
xethhung12_minio_common-0.0.3.dist-info/RECORD
